MANIFEST.in
README.md
setup.py
demo_pkg_lfr/__init__.py
demo_pkg_lfr/meta_singleton.py
demo_pkg_lfr.egg-info/PKG-INFO
demo_pkg_lfr.egg-info/SOURCES.txt
demo_pkg_lfr.egg-info/dependency_links.txt
demo_pkg_lfr.egg-info/entry_points.txt
demo_pkg_lfr.egg-info/top_level.txt