Metadata-Version: 1.1
Name: demo-pkg-lfr
Version: 0.0.1
Summary: Librairie de démo
Home-page: http://perdu.com
Author: Moi
Author-email: spam@yopmail.com
License: UNKNOWN
Platform: UNKNOWN
Classifier: Programming Language :: Python :: 3 :: Only
